{
  "NpcIdX": 368,
  "ConnectionId": 2396,
  "Name": "1788",
  "NpcId": 1788,
  "Hair": 228,
  "Face": 0,
  "Helmet": 0,
  "Armor": 0,
  "Gloves": 0,
  "Pants": 0,
  "Weapon": 1502,
  "Shield": 0,
  "Refinements": "AAAAAAAAAAAAAAAA",
  "CoordX": 3445.4,
  "CoordY": 683.4,
  "Rotation": 90,
  "Hp": 20000,
  "Mp": 20000,
  "MaxHp": 20000,
  "MaxMp": 0,
  "Unk": 10240,
  "SpawnType": 0,
  "Width": 7,
  "Chest": 119,
  "Leg": 119,
  "ConId": 368,
  "Unk2": 9,
  "Buffs": [],
  "Unk3": [],
  "Title": "Elter HQ",
  "Unk4": 50
}