{
  "NpcIdX": 161,
  "ConnectionId": 2201,
  "Name": "498",
  "NpcId": 498,
  "Hair": 20,
  "Face": 7711,
  "Helmet": 0,
  "Armor": 1811,
  "Gloves": 1841,
  "Pants": 1871,
  "Weapon": 1001,
  "Shield": 0,
  "Refinements": "AAAAAAAAAAAAAAAA",
  "CoordX": 2186.4,
  "CoordY": 2155.4,
  "Rotation": 90,
  "Hp": 20000,
  "Mp": 20000,
  "MaxHp": 20000,
  "MaxMp": 0,
  "Unk": 10240,
  "SpawnType": 0,
  "Width": 7,
  "Chest": 119,
  "Leg": 119,
  "ConId": 161,
  "Unk2": 1,
  "Buffs": [],
  "Unk3": [],
  "Title": "Elter do nono Batalhão",
  "Unk4": 50
}