{
  "NpcIdX": 0,
  "ConnectionId": 2584,
  "Name": "1020",
  "NpcId": 1020,
  "Hair": 221,
  "Face": 0,
  "Helmet": 0,
  "Armor": 0,
  "Gloves": 0,
  "Pants": 0,
  "Weapon": 0,
  "Shield": 0,
  "Refinements": "AAAAAAAAAAAAAAAA",
  "CoordX": 3171.4,
  "CoordY": 1231.4,
  "Rotation": 0,
  "Hp": 20000,
  "Mp": 20000,
  "MaxHp": 20000,
  "MaxMp": 0,
  "Unk": 0,
  "SpawnType": 0,
  "Width": 7,
  "Chest": 119,
  "Leg": 117,
  "ConId": 2058,
  "Unk2": 0,
  "Buffs": [],
  "Unk3": [],
  "Title": "",
  "Unk4": 1
}